<?xml version="1.0" encoding="utf-8"?>
<LanguageData>

  <Anneli_Faction_Ahmislan.label>安奈缇娅斯艾米斯兰</Anneli_Faction_Ahmislan.label>
  <Anneli_Faction_Ahmislan.description>艾米斯兰王国曾经是数个星球上最受欢迎的连锁主题乐园。其主要营业项目是让游客体验原汁原味的中世纪生活。在资金来源被彻底冻结之后，它并没有像其他主题乐园一样倒闭。那些幸存的员工们靠着体验项目中传授的技能和表演用道具来开垦土地、建造设施、设立机构…最终完整地还原了一整个中世纪社会。 \n她们原始的生活似乎有某种独特的吸引力，在漫长的时光中，不少流民、末日信徒、异世界穿越者、Cosplayer和全甲格斗爱好者前来投奔。不断增长得人口一方面让王国的影响力不断增长，另一方面也加深了王国内的社会危机。在愈演愈烈的危机面前，艾米斯兰王国从上到下却并没有什么行政改革和科技创新的动力，只是不断进行着具有表演性质的军事冒险——大部分情况下这些远征军都因为糟糕的军事组织和战术被打得丢盔弃甲，但所有参与者都玩得很开心。 \n如今的王国已经处于总崩溃的临界点。破产的农民、疲倦的平民、和游手好闲的骑士都在为一场所有人对所有人的斗争准备着。即便如此，王国的统治者也依旧置身事外，毕竟这个王国的繁荣与衰败，都只是故事的一部分。</Anneli_Faction_Ahmislan.description>
  <Anneli_Faction_Ahmislan.fixedName>伪造的艾米斯兰</Anneli_Faction_Ahmislan.fixedName>
  <Anneli_Faction_Ahmislan.pawnsPlural>安奈缇娅斯</Anneli_Faction_Ahmislan.pawnsPlural>
  <Anneli_Faction_Ahmislan.leaderTitle>女皇</Anneli_Faction_Ahmislan.leaderTitle>


</LanguageData>