<?xml version="1.0" encoding="utf-8" ?>
<Defs>

	<ThingDef Name="Anneli_Ahmislan_1A" ParentName="Anneli_Ahmislan_ApparelCommonBase"  Abstract="True">
		<costStuffCount>15</costStuffCount>
		<stuffCategories>
			<li>Leathery</li>
			<li>Fabric</li>
		</stuffCategories>
		<statBases>
			<WorkToMake>150</WorkToMake>
			<Mass>0.3</Mass>
			<StuffEffectMultiplierArmor>0.1</StuffEffectMultiplierArmor>
			<StuffEffectMultiplierInsulation_Cold>0.15</StuffEffectMultiplierInsulation_Cold>
			<StuffEffectMultiplierInsulation_Heat>0.15</StuffEffectMultiplierInsulation_Heat>
			<EquipDelay>1</EquipDelay>
			<Flammability>0.5</Flammability>
		</statBases>
		<equippedStatOffsets>
			<Cleanliness>0.05</Cleanliness>
		</equippedStatOffsets>
		<apparel>
			<bodyPartGroups>
				<li>Torso</li>
				<li>Shoulders</li>
				<li>Arms</li>
			</bodyPartGroups>
			<layers>
				<li>OnSkin</li>
			</layers>
			<tags>
				<li>Anneli_Ahmislan</li>
			</tags>
		</apparel>
		<graphicData>
			<drawSize>1.2</drawSize>
		</graphicData>
	</ThingDef>

<!--Anneli_Ahmislan_TornBraA-->
	<ThingDef ParentName="Anneli_Ahmislan_1A">
		<defName>Anneli_Ahmislan_TornBraA</defName>
		<description>Dyeable.</description><!-- \nDirty rags. Better than nothing. -->
		<label>(Ahmislan)1A_TornBraA</label>
		<equippedStatOffsets>
			<HungerRateMultiplier>-0.05</HungerRateMultiplier>
		</equippedStatOffsets>
		<graphicData>
			<texPath>1A/Anneli_Ahmislan_TornBraA</texPath>
			<graphicClass>Graphic_Single</graphicClass>
		</graphicData>
		<apparel>
			<wornGraphicPath>1A/Anneli_Ahmislan_TornBraA</wornGraphicPath>
			<tags>
				<li>Anneli_Ahmislan_Vagrant</li>
				<li>Anneli_Ahmislan_PeasantMan</li>
				<li>Anneli_Ahmislan_PeasantWoman</li>
				<li>Anneli_Ahmislan_Militia</li>
			</tags>
		</apparel>
		<colorGenerator Class="ColorGenerator_Options">
			<options>
				<li>
					<weight>10</weight>
					<only>(250,240,240)</only>
				</li>
			</options>
		</colorGenerator>
	</ThingDef>

<!--Anneli_Ahmislan_TornBraB-->
	<ThingDef ParentName="Anneli_Ahmislan_1A">
		<defName>Anneli_Ahmislan_TornBraB</defName>
		<description>Dyeable.</description><!-- \nDirty rags. Better than nothing. -->
		<label>(Ahmislan)1A_TornBraB</label>
		<equippedStatOffsets>
			<HungerRateMultiplier>-0.05</HungerRateMultiplier>
		</equippedStatOffsets>
		<graphicData>
			<texPath>1A/Anneli_Ahmislan_TornBraB</texPath>
			<graphicClass>Graphic_Single</graphicClass>
		</graphicData>
		<apparel>
			<wornGraphicPath>1A/Anneli_Ahmislan_TornBraB</wornGraphicPath>
			<tags>
				<li>Anneli_Ahmislan_Vagrant</li>
				<li>Anneli_Ahmislan_PeasantMan</li>
				<li>Anneli_Ahmislan_PeasantWoman</li>
				<li>Anneli_Ahmislan_Militia</li>
			</tags>
		</apparel>
		<colorGenerator Class="ColorGenerator_Options">
			<options>
				<li>
					<weight>10</weight>
					<only>(250,240,240)</only>
				</li>
			</options>
		</colorGenerator>
	</ThingDef>

<!--Anneli_Ahmislan_ChestWrap-->
	<ThingDef ParentName="Anneli_Ahmislan_1A">
		<defName>Anneli_Ahmislan_ChestWrap</defName>
		<description>Dyeable.</description><!-- \nA plain chest wrap with some ruffles. -->
		<label>(Ahmislan)1A_ChestWrap</label>
		<equippedStatOffsets>
			<NegotiationAbility>0.1</NegotiationAbility>
			<SocialImpact>0.1</SocialImpact>
		</equippedStatOffsets>
		<graphicData>
			<texPath>1A/Anneli_Ahmislan_ChestWrap</texPath>
			<graphicClass>Graphic_Single</graphicClass>
		</graphicData>
		<apparel>
			<wornGraphicPath>1A/Anneli_Ahmislan_ChestWrap</wornGraphicPath>
			<tags>
				<li>Anneli_Ahmislan_Craftswoman</li>
				<li>Anneli_Ahmislan_Merchant</li>
				<li>Anneli_Ahmislan_MercenaryInfantry</li>
				<li>Anneli_Ahmislan_MercenaryArcher</li>
			</tags>
			<useWornGraphicMask>true</useWornGraphicMask><!--Mask Applied-->
		</apparel>
		<colorGenerator Class="ColorGenerator_Options"><!--Tansparency 235-->
			<options>
				<li>
					<weight>10</weight>
					<only>(250,240,240,235)</only>
				</li>
			</options>
		</colorGenerator>
	</ThingDef>

</Defs>